jupdoc/__init__.py
jupdoc/__main__.py
jupdoc/convert.py
jupdoc/main.py
jupdoc/upload.py
jupdoc-0.1.4.data/scripts/convert.py
jupdoc-0.1.4.data/scripts/main.py
jupdoc-0.1.4.dist-info/LICENSE
jupdoc-0.1.4.dist-info/METADATA
jupdoc-0.1.4.dist-info/WHEEL
jupdoc-0.1.4.dist-info/entry_points.txt
jupdoc-0.1.4.dist-info/top_level.txt
jupdoc-0.1.4.dist-info/RECORD
