Metadata-Version: 2.1
Name: jupdoc
Version: 0.1.4
Summary: A package to convert Jupyter Notebooks to Word Documents (and other quarto supported formats) and upload them to Google Drive, with support for multiple user roles, using Quarto.
Home-page: https://github.com/wadhwaniAI/jupdoc
Author: Ashish Papanai
Author-email: ashishp@wadhwaniai.org
License: MIT
Classifier: Programming Language :: Python :: 3
Classifier: License :: OSI Approved :: MIT License
Classifier: Operating System :: OS Independent
License-File: LICENSE
Requires-Dist: nbconvert
Requires-Dist: nbformat
Requires-Dist: PyYAML
Requires-Dist: setuptools
Requires-Dist: coloredlogs
Requires-Dist: google-api-python-client
Requires-Dist: google-auth-httplib2
Requires-Dist: google-auth-oauthlib
Requires-Dist: google-auth
Requires-Dist: google-api-core
